{
	"configurations" : 
	[
		{
			"directories" : 
			[
				{
					"build" : ".",
					"childIndexes" : 
					[
						1,
						9
					],
					"hasInstallRule" : true,
					"jsonFile" : "directory-.-Debug-f5ebdc15457944623624.json",
					"minimumCMakeVersion" : 
					{
						"string" : "3.16"
					},
					"projectIndex" : 0,
					"source" : "."
				},
				{
					"build" : "src",
					"childIndexes" : 
					[
						2
					],
					"hasInstallRule" : true,
					"jsonFile" : "directory-src-Debug-b6cf2213fc5053b67c22.json",
					"minimumCMakeVersion" : 
					{
						"string" : "3.16"
					},
					"parentIndex" : 0,
					"projectIndex" : 1,
					"source" : "src",
					"targetIndexes" : 
					[
						1
					]
				},
				{
					"build" : "src/libs/SFML",
					"childIndexes" : 
					[
						3
					],
					"hasInstallRule" : true,
					"jsonFile" : "directory-src.libs.SFML-Debug-d5d85fa024a4e0de623e.json",
					"minimumCMakeVersion" : 
					{
						"string" : "3.16"
					},
					"parentIndex" : 1,
					"projectIndex" : 2,
					"source" : "src/libs/SFML"
				},
				{
					"build" : "src/libs/SFML/src/SFML",
					"childIndexes" : 
					[
						4,
						5,
						6,
						7,
						8
					],
					"hasInstallRule" : true,
					"jsonFile" : "directory-src.libs.SFML.src.SFML-Debug-931de7e8cfb418eaf47f.json",
					"minimumCMakeVersion" : 
					{
						"string" : "3.16"
					},
					"parentIndex" : 2,
					"projectIndex" : 2,
					"source" : "src/libs/SFML/src/SFML"
				},
				{
					"build" : "src/libs/SFML/src/SFML/System",
					"hasInstallRule" : true,
					"jsonFile" : "directory-src.libs.SFML.src.SFML.System-Debug-ad0773131b910cb385e3.json",
					"minimumCMakeVersion" : 
					{
						"string" : "3.16"
					},
					"parentIndex" : 3,
					"projectIndex" : 2,
					"source" : "src/libs/SFML/src/SFML/System",
					"targetIndexes" : 
					[
						9
					]
				},
				{
					"build" : "src/libs/SFML/src/SFML/Window",
					"hasInstallRule" : true,
					"jsonFile" : "directory-src.libs.SFML.src.SFML.Window-Debug-100e41069503eabc61b6.json",
					"minimumCMakeVersion" : 
					{
						"string" : "3.16"
					},
					"parentIndex" : 3,
					"projectIndex" : 2,
					"source" : "src/libs/SFML/src/SFML/Window",
					"targetIndexes" : 
					[
						10
					]
				},
				{
					"build" : "src/libs/SFML/src/SFML/Network",
					"hasInstallRule" : true,
					"jsonFile" : "directory-src.libs.SFML.src.SFML.Network-Debug-89b8425fe27901ab283e.json",
					"minimumCMakeVersion" : 
					{
						"string" : "3.16"
					},
					"parentIndex" : 3,
					"projectIndex" : 2,
					"source" : "src/libs/SFML/src/SFML/Network",
					"targetIndexes" : 
					[
						8
					]
				},
				{
					"build" : "src/libs/SFML/src/SFML/Graphics",
					"hasInstallRule" : true,
					"jsonFile" : "directory-src.libs.SFML.src.SFML.Graphics-Debug-da47c6a8f1ec34bc9081.json",
					"minimumCMakeVersion" : 
					{
						"string" : "3.16"
					},
					"parentIndex" : 3,
					"projectIndex" : 2,
					"source" : "src/libs/SFML/src/SFML/Graphics",
					"targetIndexes" : 
					[
						7
					]
				},
				{
					"build" : "src/libs/SFML/src/SFML/Audio",
					"hasInstallRule" : true,
					"jsonFile" : "directory-src.libs.SFML.src.SFML.Audio-Debug-a23b99e31cec0cc22097.json",
					"minimumCMakeVersion" : 
					{
						"string" : "3.16"
					},
					"parentIndex" : 3,
					"projectIndex" : 2,
					"source" : "src/libs/SFML/src/SFML/Audio",
					"targetIndexes" : 
					[
						6
					]
				},
				{
					"build" : "test",
					"childIndexes" : 
					[
						10
					],
					"hasInstallRule" : true,
					"jsonFile" : "directory-test-Debug-451c0598f41488bb20b9.json",
					"minimumCMakeVersion" : 
					{
						"string" : "3.16"
					},
					"parentIndex" : 0,
					"projectIndex" : 3,
					"source" : "test",
					"targetIndexes" : 
					[
						0
					]
				},
				{
					"build" : "test/lib/googletest-main/googletest-main",
					"childIndexes" : 
					[
						11
					],
					"hasInstallRule" : true,
					"jsonFile" : "directory-test.lib.googletest-main.googletest-main-Debug-ca98d03e4e48b2d8f75b.json",
					"minimumCMakeVersion" : 
					{
						"string" : "3.5"
					},
					"parentIndex" : 9,
					"projectIndex" : 4,
					"source" : "test/lib/googletest-main/googletest-main"
				},
				{
					"build" : "test/lib/googletest-main/googletest-main/googlemock",
					"childIndexes" : 
					[
						12
					],
					"hasInstallRule" : true,
					"jsonFile" : "directory-test.lib.googletest-main.googletest-main.googlemock-Debug-403391bcbcdc89321332.json",
					"minimumCMakeVersion" : 
					{
						"string" : "3.5"
					},
					"parentIndex" : 10,
					"projectIndex" : 5,
					"source" : "test/lib/googletest-main/googletest-main/googlemock",
					"targetIndexes" : 
					[
						2,
						3
					]
				},
				{
					"build" : "test/lib/googletest-main/googletest-main/googletest",
					"hasInstallRule" : true,
					"jsonFile" : "directory-test.lib.googletest-main.googletest-main.googletest-Debug-b922eb9b66cbb5dbd913.json",
					"minimumCMakeVersion" : 
					{
						"string" : "3.5"
					},
					"parentIndex" : 11,
					"projectIndex" : 6,
					"source" : "test/lib/googletest-main/googletest-main/googletest",
					"targetIndexes" : 
					[
						4,
						5
					]
				}
			],
			"name" : "Debug",
			"projects" : 
			[
				{
					"childIndexes" : 
					[
						1,
						3
					],
					"directoryIndexes" : 
					[
						0
					],
					"name" : "game_project"
				},
				{
					"childIndexes" : 
					[
						2
					],
					"directoryIndexes" : 
					[
						1
					],
					"name" : "game",
					"parentIndex" : 0,
					"targetIndexes" : 
					[
						1
					]
				},
				{
					"directoryIndexes" : 
					[
						2,
						3,
						4,
						5,
						6,
						7,
						8
					],
					"name" : "SFML",
					"parentIndex" : 1,
					"targetIndexes" : 
					[
						6,
						7,
						8,
						9,
						10
					]
				},
				{
					"childIndexes" : 
					[
						4
					],
					"directoryIndexes" : 
					[
						9
					],
					"name" : "Google_tests",
					"parentIndex" : 0,
					"targetIndexes" : 
					[
						0
					]
				},
				{
					"childIndexes" : 
					[
						5
					],
					"directoryIndexes" : 
					[
						10
					],
					"name" : "googletest-distribution",
					"parentIndex" : 3
				},
				{
					"childIndexes" : 
					[
						6
					],
					"directoryIndexes" : 
					[
						11
					],
					"name" : "gmock",
					"parentIndex" : 4,
					"targetIndexes" : 
					[
						2,
						3
					]
				},
				{
					"directoryIndexes" : 
					[
						12
					],
					"name" : "gtest",
					"parentIndex" : 5,
					"targetIndexes" : 
					[
						4,
						5
					]
				}
			],
			"targets" : 
			[
				{
					"directoryIndex" : 9,
					"id" : "Google_Tests_run::@36f028580bb02cc8272a",
					"jsonFile" : "target-Google_Tests_run-Debug-449fc4d50792f7c3fd61.json",
					"name" : "Google_Tests_run",
					"projectIndex" : 3
				},
				{
					"directoryIndex" : 1,
					"id" : "game::@145eef247bfb46b6828c",
					"jsonFile" : "target-game-Debug-dc7ecc9b281e41f48cde.json",
					"name" : "game",
					"projectIndex" : 1
				},
				{
					"directoryIndex" : 11,
					"id" : "gmock::@e7f650417929b231138b",
					"jsonFile" : "target-gmock-Debug-b14ff3ee94aec8c742de.json",
					"name" : "gmock",
					"projectIndex" : 5
				},
				{
					"directoryIndex" : 11,
					"id" : "gmock_main::@e7f650417929b231138b",
					"jsonFile" : "target-gmock_main-Debug-70636b213487663b52ba.json",
					"name" : "gmock_main",
					"projectIndex" : 5
				},
				{
					"directoryIndex" : 12,
					"id" : "gtest::@a1db4f116c42a4432c00",
					"jsonFile" : "target-gtest-Debug-fcc692732340bbf3c9c2.json",
					"name" : "gtest",
					"projectIndex" : 6
				},
				{
					"directoryIndex" : 12,
					"id" : "gtest_main::@a1db4f116c42a4432c00",
					"jsonFile" : "target-gtest_main-Debug-8d4188fc98367fcfe0ca.json",
					"name" : "gtest_main",
					"projectIndex" : 6
				},
				{
					"directoryIndex" : 8,
					"id" : "sfml-audio::@3191b9802bc81c7edd35",
					"jsonFile" : "target-sfml-audio-Debug-52cc43dd4c076b83efc0.json",
					"name" : "sfml-audio",
					"projectIndex" : 2
				},
				{
					"directoryIndex" : 7,
					"id" : "sfml-graphics::@eec4edff233c9443932d",
					"jsonFile" : "target-sfml-graphics-Debug-1b4d583a5d1c7599147a.json",
					"name" : "sfml-graphics",
					"projectIndex" : 2
				},
				{
					"directoryIndex" : 6,
					"id" : "sfml-network::@4ec8c9a40a724e5ca173",
					"jsonFile" : "target-sfml-network-Debug-38692414576dcb736129.json",
					"name" : "sfml-network",
					"projectIndex" : 2
				},
				{
					"directoryIndex" : 4,
					"id" : "sfml-system::@b22d2b36c8c404f53102",
					"jsonFile" : "target-sfml-system-Debug-39fa116e94b4bcfcf23b.json",
					"name" : "sfml-system",
					"projectIndex" : 2
				},
				{
					"directoryIndex" : 5,
					"id" : "sfml-window::@db149f23e8457c8165c4",
					"jsonFile" : "target-sfml-window-Debug-69e53d8ffe75878f09dc.json",
					"name" : "sfml-window",
					"projectIndex" : 2
				}
			]
		}
	],
	"kind" : "codemodel",
	"paths" : 
	{
		"build" : "/media/stepan/Windows 10 Compact/Users/Stephan/Desktop/vs_code_game/build",
		"source" : "/media/stepan/Windows 10 Compact/Users/Stephan/Desktop/vs_code_game"
	},
	"version" : 
	{
		"major" : 2,
		"minor" : 4
	}
}
